JfrogPypiTrial/HelloWorld.py
JfrogPypiTrial/__init__.py
jfrog_pypi_trial-200.0.0.dist-info/licenses/LICENSE
jfrog_pypi_trial-200.0.0.dist-info/METADATA
jfrog_pypi_trial-200.0.0.dist-info/WHEEL
jfrog_pypi_trial-200.0.0.dist-info/top_level.txt
jfrog_pypi_trial-200.0.0.dist-info/RECORD
