Metadata-Version: 2.4
Name: jfrog-pypi-trial
Version: 200.0.0
Summary: Add your description here
Requires-Python: >=3.13
License-File: LICENSE
Dynamic: license-file
